Code/CGESystem.py
Code/Calibration.py
Code/Consumer.py
Code/MacroEconomy.py
Code/Producer.py
Code/Run.py
Code/__init__.py
standard_chn_cge-0.2.dist-info/METADATA
standard_chn_cge-0.2.dist-info/WHEEL
standard_chn_cge-0.2.dist-info/entry_points.txt
standard_chn_cge-0.2.dist-info/top_level.txt
standard_chn_cge-0.2.dist-info/RECORD
