Metadata-Version: 2.1
Name: standard_chn_cge
Version: 0.2
Summary: This model is a simplified version of a CGE model for China, including 2-factor inputs, 3 sectors, 2 final consumers, investment/saving account and global trade. We update the technology and inventory account
Home-page: https://junexqu.github.io/
Author: Junxi Qu (HKU)
Author-email: qujunxi@connect.hku.hk
Classifier: Programming Language :: Python :: 3
Classifier: License :: OSI Approved :: MIT License
Requires-Python: >=3.6
Requires-Dist: numpy
Requires-Dist: pandas
Requires-Dist: scipy
